pretix_nextcloud_products/__init__.py
pretix_nextcloud_products/apps.py
pretix_nextcloud_products/forms.py
pretix_nextcloud_products/models.py
pretix_nextcloud_products/signals.py
pretix_nextcloud_products/ticketoutput.py
pretix_nextcloud_products/locale/django.pot
pretix_nextcloud_products/locale/de/LC_MESSAGES/django.mo
pretix_nextcloud_products/locale/de/LC_MESSAGES/django.po
pretix_nextcloud_products/locale/de_Informal/.gitkeep
pretix_nextcloud_products/locale/de_Informal/LC_MESSAGES/django.mo
pretix_nextcloud_products/locale/de_Informal/LC_MESSAGES/django.po
pretix_nextcloud_products/migrations/0001_initial.py
pretix_nextcloud_products/migrations/__init__.py
pretix_nextcloud_products/static/pretix_nextcloud_products/.gitkeep
pretix_nextcloud_products/templates/pretix_nextcloud_products/.gitkeep
pretix_nextcloud_products-1.0.1.dist-info/licenses/LICENSE
pretix_nextcloud_products-1.0.1.dist-info/METADATA
pretix_nextcloud_products-1.0.1.dist-info/WHEEL
pretix_nextcloud_products-1.0.1.dist-info/entry_points.txt
pretix_nextcloud_products-1.0.1.dist-info/top_level.txt
pretix_nextcloud_products-1.0.1.dist-info/RECORD
