Metadata-Version: 2.4
Name: pretix-nextcloud-products
Version: 1.0.1
Summary: Instead of ticket downloads, create share links for Nextcloud
Author-email: Jonathan Weth <dev@jonathanweth.de>
Maintainer-email: Jonathan Weth <dev@jonathanweth.de>
License: Apache
Project-URL: homepage, https://codeberg.org/hansegucker/pretix-nextcloud-products
Project-URL: repository, https://codeberg.org/hansegucker/pretix-nextcloud-products
Keywords: pretix
License-File: LICENSE
Requires-Dist: defusedxml
Requires-Dist: requests
Dynamic: license-file
